{
  "/_not-found/page": "app/_not-found/page.js",
  "/_global-error/page": "app/_global-error/page.js",
  "/favicon.ico/route": "app/favicon.ico/route.js",
  "/manifest.webmanifest/route": "app/manifest.webmanifest/route.js",
  "/dashboard/page": "app/dashboard/page.js",
  "/household/page": "app/household/page.js",
  "/inventory/page": "app/inventory/page.js",
  "/meals/page": "app/meals/page.js",
  "/onboarding/page": "app/onboarding/page.js",
  "/page": "app/page.js",
  "/scan/page": "app/scan/page.js",
  "/settings/page": "app/settings/page.js",
  "/shopping-list/page": "app/shopping-list/page.js",
  "/sign-in/page": "app/sign-in/page.js",
  "/sign-up/page": "app/sign-up/page.js",
  "/forgot-password/page": "app/forgot-password/page.js"
}